erpbrasil.edoc.pdf-1.2.1-nspkg.pth
erpbrasil/edoc/pdf/__init__.py
erpbrasil/edoc/pdf/__main__.py
erpbrasil/edoc/pdf/base.py
erpbrasil/edoc/pdf/cli.py
erpbrasil/edoc/pdf/danfe.odt
erpbrasil/edoc/pdf/danfe_formata.py
erpbrasil/edoc/pdf/nfe.py
erpbrasil.edoc.pdf-1.2.1.dist-info/AUTHORS.rst
erpbrasil.edoc.pdf-1.2.1.dist-info/LICENSE
erpbrasil.edoc.pdf-1.2.1.dist-info/METADATA
erpbrasil.edoc.pdf-1.2.1.dist-info/WHEEL
erpbrasil.edoc.pdf-1.2.1.dist-info/entry_points.txt
erpbrasil.edoc.pdf-1.2.1.dist-info/namespace_packages.txt
erpbrasil.edoc.pdf-1.2.1.dist-info/top_level.txt
erpbrasil.edoc.pdf-1.2.1.dist-info/RECORD
