Metadata-Version: 2.1
Name: erpbrasil.edoc.pdf
Version: 1.2.1
Summary: Impressão de documentos fiscais a partir do XML: NF-E, NFC-E, CT-E, MDF-E, GNRE e etc.
Home-page: https://github.com/erpbrasil/erpbrasil.edoc.pdf
Author: KMEE
Author-email: dev@kmee.com.br
License: MIT
Platform: UNKNOWN
Classifier: Development Status :: 5 - Production/Stable
Classifier: Intended Audience :: Developers
Classifier: License :: OSI Approved :: MIT License
Classifier: Operating System :: Unix
Classifier: Operating System :: POSIX
Classifier: Operating System :: Microsoft :: Windows
Classifier: Programming Language :: Python
Classifier: Programming Language :: Python :: 3
Classifier: Programming Language :: Python :: 3.5
Classifier: Programming Language :: Python :: 3.6
Classifier: Programming Language :: Python :: 3.7
Classifier: Programming Language :: Python :: Implementation :: CPython
Classifier: Programming Language :: Python :: Implementation :: PyPy
Classifier: Topic :: Utilities
Requires-Python: >=3.5, !=3.0.*, !=3.1.*, !=3.2.*, !=3.3.*
License-File: LICENSE
License-File: AUTHORS.rst
